bstq/__init__.py
bstq/bstq.py
bstq/exceptions.py
bstq/test.py
bstq-1.0.1.dist-info/LICENCE.txt
bstq-1.0.1.dist-info/METADATA
bstq-1.0.1.dist-info/WHEEL
bstq-1.0.1.dist-info/top_level.txt
bstq-1.0.1.dist-info/RECORD
