Metadata-Version: 2.1
Name: bstq
Version: 1.0.1
Summary: Comphrensive Library for Binary Search Trees.
Home-page: https://github.com/omkashyap007/Binary-Search-Tree-Library/tree/master
Author: Om Kashyap
Author-email: omkashyapcric@gmail.com
License: MIT
Keywords: bst,binary search tree,binarytree,binary tree
Classifier: Development Status :: 5 - Production/Stable
Classifier: Intended Audience :: Education
Classifier: Operating System :: Microsoft :: Windows :: Windows 10
Classifier: License :: OSI Approved :: MIT License
Classifier: Programming Language :: Python :: 3
License-File: LICENCE.txt
